mac_4mater.py
mac_4mater-1.0.dist-info/METADATA
mac_4mater-1.0.dist-info/WHEEL
mac_4mater-1.0.dist-info/top_level.txt
mac_4mater-1.0.dist-info/RECORD
