Metadata-Version: 2.1
Name: mac-4mater
Version: 1.0
Summary: convert mac to required format
Home-page: https://github.com/myxx921/mac_4mater
Author: myxx921
Author-email: myxx921@gmail.com
